<?xml version="1.0" encoding="utf-8" ?><dwsync><file name="background-only.png" server="snowgate.com/snowgate.com/dev/" local="3459130200" remote="3459130200" Dst="-1" /><file name="grain.png" server="snowgate.com/snowgate.com/dev/" local="3459130200" remote="3459130200" Dst="-1" /><file name="photo.png" server="snowgate.com/snowgate.com/dev/" local="3459130200" remote="3459130200" Dst="-1" /><file name="puckered.png" server="snowgate.com/snowgate.com/dev/" local="3459130200" remote="3459130200" Dst="-1" /><file name="scroll-a-video.png" server="snowgate.com/snowgate.com/dev/" local="3459130200" remote="3459130200" Dst="-1" /><file name="slide2.jpg" server="snowgate.com/snowgate.com/dev/" local="3459130200" remote="3459130200" Dst="-1" /><file name="slide3.jpg" server="snowgate.com/snowgate.com/dev/" local="3459130200" remote="3459130200" Dst="-1" /><file name="slide4.jpg" server="snowgate.com/snowgate.com/dev/" local="3459130200" remote="3459130200" Dst="-1" /><file name="smashing-logo.png" server="snowgate.com/snowgate.com/dev/" local="3459130200" remote="3459130200" Dst="-1" /><file name="theend.png" server="snowgate.com/snowgate.com/dev/" local="3459130200" remote="3459130200" Dst="-1" /><file name="tutorial-title.png" server="snowgate.com/snowgate.com/dev/" local="3459130200" remote="3459130200" Dst="-1" /></dwsync>